econicer/__init__.py
econicer/__main__.py
econicer/account.py
econicer/accountManager.py
econicer/auxiliary.py
econicer/ecoplot.py
econicer/fileIO.py
econicer/glumt.mplrc
econicer/report.py
econicer/settings.py
econicer-0.23.dist-info/LICENSE
econicer-0.23.dist-info/METADATA
econicer-0.23.dist-info/WHEEL
econicer-0.23.dist-info/top_level.txt
econicer-0.23.dist-info/RECORD
