Metadata-Version: 2.1
Name: econicer
Version: 0.23
Summary: A small program to analyse financial transactions
Home-page: https://github.com/Spiony/econicer
Author: spiony
Author-email: glumt@protonmail.com
License: UNKNOWN
Platform: UNKNOWN
Classifier: Programming Language :: Python :: 3
Classifier: Operating System :: OS Independent
Classifier: License :: OSI Approved :: GNU General Public License v3 (GPLv3)
Requires-Python: >=3.8
License-File: LICENSE
Requires-Dist: matplotlib (>=3.4.1)
Requires-Dist: PyLaTeX (>=1.4.1)
Requires-Dist: pandas (>=1.2.3)
